<?xml version="1.0" encoding="UTF-8"?><rules>
<rule>
<name>IFTTT</name>
<metric>test_m</metric>
<tagsGroupingStrategy>ALL_TAGS</tagsGroupingStrategy>
<expression><![CDATA[value > 1]]></expression>
<window>length(1)</window>
<severity>WARNING</severity>
<alertOpenMessage><![CDATA[${received_datetime}	${status}	${severity}	${rule}	${metric}	${entity}	${tags}	${value}]]></alertOpenMessage>
<alertMessage><![CDATA[${received_datetime}	${status}	${severity}	${rule}	${metric}	${entity}	${tags}	${value}]]></alertMessage>
<alertCancellationMessage><![CDATA[${received_datetime}	${status}	${severity}	${rule}	${metric}	${entity}	${tags}	${value}]]></alertCancellationMessage>
<alertStrategy>
<type>ALL</type>
<intervalCount>5</intervalCount>
<intervalUnit>MINUTE</intervalUnit>
</alertStrategy>
<lastUpdated>1513002450846</lastUpdated>
<enabled>true</enabled>
<disableEntityGrouping>false</disableEntityGrouping>
<leavingEvents>true</leavingEvents>
<logOutput>false</logOutput>
<owner>alexey</owner>
<actionStrategy>
<type>ALL</type>
<intervalCount>5</intervalCount>
<intervalUnit>MINUTE</intervalUnit>
</actionStrategy>
<discardPreviousValues>true</discardPreviousValues>
<webNotification>
<disabled>false</disabled>
<rule-name>IFTTT</rule-name>
<repeat-interval>
<type>ALL</type>
<intervalCount>6</intervalCount>
<intervalUnit>MINUTE</intervalUnit>
</repeat-interval>
<name>Web Service Notification id=1</name>
<use-in-threshold-only>false</use-in-threshold-only>
<first-details>false</first-details>
<repeat-details>false</repeat-details>
<cancel-details>false</cancel-details>
<first-screenshot>false</first-screenshot>
<repeat-screenshot>false</repeat-screenshot>
<cancel-screenshot>false</cancel-screenshot>
<webNotificationConfigName>custom-ifttt</webNotificationConfigName>
<firstWebConfigParameters>
<key>entity</key>
<value/>
</firstWebConfigParameters>
<firstWebConfigParameters>
<key>rule</key>
<value/>
</firstWebConfigParameters>
<firstWebConfigParameters>
<key>status</key>
<value/>
</firstWebConfigParameters>
<firstWebConfigParameters>
<key>webhook_name</key>
<value>atsd_custom_webhook</value>
</firstWebConfigParameters>
<repeatWebConfigParameters>
<key>entity</key>
<value/>
</repeatWebConfigParameters>
<repeatWebConfigParameters>
<key>rule</key>
<value/>
</repeatWebConfigParameters>
<repeatWebConfigParameters>
<key>status</key>
<value/>
</repeatWebConfigParameters>
<repeatWebConfigParameters>
<key>webhook_name</key>
<value>atsd_custom_webhook</value>
</repeatWebConfigParameters>
<cancelWebConfigParameters>
<key>entity</key>
<value/>
</cancelWebConfigParameters>
<cancelWebConfigParameters>
<key>rule</key>
<value/>
</cancelWebConfigParameters>
<cancelWebConfigParameters>
<key>status</key>
<value/>
</cancelWebConfigParameters>
<cancelWebConfigParameters>
<key>webhook_name</key>
<value>atsd_custom_webhook</value>
</cancelWebConfigParameters>
<first-enabled>true</first-enabled>
<repeat-enabled>true</repeat-enabled>
<cancel-enabled>true</cancel-enabled>
</webNotification>
<ruleTable/>
<alertLoggerName>atsd.alert.default</alertLoggerName>
<derivedCommandEnabled>false</derivedCommandEnabled>
<derivedCommandStrategy>
<type>ALL</type>
<intervalCount>5</intervalCount>
<intervalUnit>MINUTE</intervalUnit>
</derivedCommandStrategy>
</rule>
</rules>
