<list>
  <com.axibase.collector.model.job.jmx.JmxJobConfig>
    <name>kafka-jmx</name>
    <cronExpression>R 0/10 * * * ?</cronExpression>
    <enabled>false</enabled>
    <jobType>JMX</jobType>
    <defaultTags/>
    <checkLastTime>false</checkLastTime>
    <commitInterval>10</commitInterval>
    <errorThreshold>0</errorThreshold>
    <configurations>
      <com.axibase.collector.model.job.jmx.JmxConfiguration>
        <name>kafka-series</name>
        <host>kafka-host</host>
        <port>1099</port>
        <userName></userName>
        <password></password>
        <trackingMBeans>
          <com.axibase.collector.model.job.jmx.TrackingMBean>
            <objectName>kafka.server:name=*,type=BrokerTopicMetrics</objectName>
            <attributes>*</attributes>
            <propertyType></propertyType>
          </com.axibase.collector.model.job.jmx.TrackingMBean>
          <com.axibase.collector.model.job.jmx.TrackingMBean>
            <objectName>kafka.controller:name=*,type=ControllerStats</objectName>
            <attributes>*</attributes>
            <propertyType></propertyType>
          </com.axibase.collector.model.job.jmx.TrackingMBean>
          <com.axibase.collector.model.job.jmx.TrackingMBean>
            <objectName>kafka.server:fetcherType=*,name=*,type=DelayedFetchMetrics</objectName>
            <attributes>*</attributes>
            <propertyType></propertyType>
          </com.axibase.collector.model.job.jmx.TrackingMBean>
          <com.axibase.collector.model.job.jmx.TrackingMBean>
            <objectName>kafka.server:delayedOperation=*,name=*,type=DelayedOperationPurgatory</objectName>
            <attributes>*</attributes>
            <propertyType></propertyType>
          </com.axibase.collector.model.job.jmx.TrackingMBean>
          <com.axibase.collector.model.job.jmx.TrackingMBean>
            <objectName>kafka.server:type=Fetch</objectName>
            <attributes>*</attributes>
            <propertyType></propertyType>
          </com.axibase.collector.model.job.jmx.TrackingMBean>
          <com.axibase.collector.model.job.jmx.TrackingMBean>
            <objectName>kafka.server:clientId=*,name=*,partition=*,topic=*,type=FetcherLagMetrics</objectName>
            <attributes>*</attributes>
            <propertyType></propertyType>
          </com.axibase.collector.model.job.jmx.TrackingMBean>
          <com.axibase.collector.model.job.jmx.TrackingMBean>
            <objectName>kafka.server:brokerHost=*,brokerPort=*,clientId=*,name=*,type=FetcherStats</objectName>
            <attributes>*</attributes>
            <propertyType></propertyType>
          </com.axibase.collector.model.job.jmx.TrackingMBean>
          <com.axibase.collector.model.job.jmx.TrackingMBean>
            <objectName>kafka.coordinator.group:name=*,type=GroupMetadataManager</objectName>
            <attributes>*</attributes>
            <propertyType></propertyType>
          </com.axibase.collector.model.job.jmx.TrackingMBean>
          <com.axibase.collector.model.job.jmx.TrackingMBean>
            <objectName>kafka.controller:name=*,type=KafkaController</objectName>
            <attributes>*</attributes>
            <propertyType></propertyType>
          </com.axibase.collector.model.job.jmx.TrackingMBean>
          <com.axibase.collector.model.job.jmx.TrackingMBean>
            <objectName>kafka.server:name=*,type=KafkaRequestHandlerPool</objectName>
            <attributes>*</attributes>
            <propertyType></propertyType>
          </com.axibase.collector.model.job.jmx.TrackingMBean>
          <com.axibase.collector.model.job.jmx.TrackingMBean>
            <objectName>kafka.server:name=*,type=KafkaServer</objectName>
            <attributes>*</attributes>
            <propertyType></propertyType>
          </com.axibase.collector.model.job.jmx.TrackingMBean>
          <com.axibase.collector.model.job.jmx.TrackingMBean>
            <objectName>kafka.server:type=LeaderReplication</objectName>
            <attributes>*</attributes>
            <propertyType></propertyType>
          </com.axibase.collector.model.job.jmx.TrackingMBean>
          <com.axibase.collector.model.job.jmx.TrackingMBean>
            <objectName>kafka.server:type=Produce</objectName>
            <attributes>*</attributes>
            <propertyType></propertyType>
          </com.axibase.collector.model.job.jmx.TrackingMBean>
          <com.axibase.collector.model.job.jmx.TrackingMBean>
            <objectName>kafka.server:name=*,type=ReplicaManager</objectName>
            <attributes>*</attributes>
            <propertyType></propertyType>
          </com.axibase.collector.model.job.jmx.TrackingMBean>
          <com.axibase.collector.model.job.jmx.TrackingMBean>
            <objectName>kafka.server:type=Request</objectName>
            <attributes>*</attributes>
            <propertyType></propertyType>
          </com.axibase.collector.model.job.jmx.TrackingMBean>
          <com.axibase.collector.model.job.jmx.TrackingMBean>
            <objectName>kafka.network:name=*,processor=*,type=RequestChannel</objectName>
            <attributes>*</attributes>
            <propertyType></propertyType>
          </com.axibase.collector.model.job.jmx.TrackingMBean>
          <com.axibase.collector.model.job.jmx.TrackingMBean>
            <objectName>kafka.network:name=*,type=SocketServer</objectName>
            <attributes>*</attributes>
            <propertyType></propertyType>
          </com.axibase.collector.model.job.jmx.TrackingMBean>
          <com.axibase.collector.model.job.jmx.TrackingMBean>
            <objectName>kafka.server:name=*,type=ZooKeeperClientMetrics</objectName>
            <attributes>*</attributes>
            <propertyType></propertyType>
          </com.axibase.collector.model.job.jmx.TrackingMBean>
          <com.axibase.collector.model.job.jmx.TrackingMBean>
            <objectName>kafka.server:type=kafka-metrics-count</objectName>
            <attributes>*</attributes>
            <propertyType></propertyType>
          </com.axibase.collector.model.job.jmx.TrackingMBean>
          <com.axibase.collector.model.job.jmx.TrackingMBean>
            <objectName>kafka.server:broker-id=*,fetcher-id=*,type=replica-fetcher-metrics</objectName>
            <attributes>*</attributes>
            <propertyType></propertyType>
          </com.axibase.collector.model.job.jmx.TrackingMBean>
          <com.axibase.collector.model.job.jmx.TrackingMBean>
            <objectName>kafka.server:listener=*,networkProcessor=*,type=socket-server-metrics</objectName>
            <attributes>*</attributes>
            <propertyType></propertyType>
          </com.axibase.collector.model.job.jmx.TrackingMBean>
          <com.axibase.collector.model.job.jmx.TrackingMBean>
            <objectName>kafka.server:type=txn-marker-channel-metrics</objectName>
            <attributes>*</attributes>
            <propertyType></propertyType>
          </com.axibase.collector.model.job.jmx.TrackingMBean>
          <com.axibase.collector.model.job.jmx.TrackingMBean>
            <objectName>kafka.log:name=*,partition=*,topic!=_*,type=Log</objectName>
            <attributes>*</attributes>
            <propertyType></propertyType>
          </com.axibase.collector.model.job.jmx.TrackingMBean>
          <com.axibase.collector.model.job.jmx.TrackingMBean>
            <objectName>kafka.cluster:name=*,partition=*,topic!=_*,type=Partition</objectName>
            <attributes>*</attributes>
            <propertyType></propertyType>
          </com.axibase.collector.model.job.jmx.TrackingMBean>
          <com.axibase.collector.model.job.jmx.TrackingMBean>
            <objectName>kafka.server:name=*,topic!=_*,type=BrokerTopicMetrics</objectName>
            <attributes>*</attributes>
            <propertyType></propertyType>
          </com.axibase.collector.model.job.jmx.TrackingMBean>
        </trackingMBeans>
        <entity></entity>
        <metricPrefix>jmx.${domain}.${type}.${name}.</metricPrefix>
        <propertyTypePrefix></propertyTypePrefix>
        <serviceName></serviceName>
        <excludedMetrics>
          <string>75thPercentile</string>
          <string>95thPercentile</string>
          <string>98thPercentile</string>
          <string>999thPercentile</string>
          <string>EventType</string>
          <string>FifteenMinuteRate</string>
          <string>LatencyUnit</string>
          <string>RateUnit</string>
          <string>StdDev</string>
        </excludedMetrics>
        <excludedProperties/>
        <seriesTags/>
        <putType>SERIES</putType>
      </com.axibase.collector.model.job.jmx.JmxConfiguration>
      <com.axibase.collector.model.job.jmx.JmxConfiguration>
        <name>kafka-properties</name>
        <host>kafka-host</host>
        <port>1099</port>
        <userName></userName>
        <password></password>
        <trackingMBeans>
          <com.axibase.collector.model.job.jmx.TrackingMBean>
              <objectName>kafka.server:name=*,type=KafkaServer</objectName>
              <attributes>Value</attributes>
              <propertyType></propertyType>
          </com.axibase.collector.model.job.jmx.TrackingMBean>
          <com.axibase.collector.model.job.jmx.TrackingMBean>
              <objectName>kafka.log:name=*,partition=*,topic=t*,type=Log</objectName>
              <attributes>Value</attributes>
              <propertyType></propertyType>
          </com.axibase.collector.model.job.jmx.TrackingMBean>
          <com.axibase.collector.model.job.jmx.TrackingMBean>
              <objectName>kafka.cluster:name=*,partition=*,topic=t*,type=Partition</objectName>
              <attributes>Value</attributes>
              <propertyType></propertyType>
          </com.axibase.collector.model.job.jmx.TrackingMBean>
          <com.axibase.collector.model.job.jmx.TrackingMBean>
              <objectName>kafka.server:type=app-info</objectName>
              <attributes>commit-id</attributes>
              <propertyType></propertyType>
          </com.axibase.collector.model.job.jmx.TrackingMBean>
          <com.axibase.collector.model.job.jmx.TrackingMBean>
              <objectName>kafka.controller:name=*,type=KafkaController</objectName>
              <attributes>Value</attributes>
              <propertyType></propertyType>
          </com.axibase.collector.model.job.jmx.TrackingMBean>
          <com.axibase.collector.model.job.jmx.TrackingMBean>
              <objectName>kafka.log:name=*,partition=*,topic=a*,type=Log</objectName>
              <attributes>Value</attributes>
              <propertyType></propertyType>
          </com.axibase.collector.model.job.jmx.TrackingMBean>
          <com.axibase.collector.model.job.jmx.TrackingMBean>
              <objectName>kafka.cluster:name=*,partition=*,topic=a*,type=Partition</objectName>
              <attributes>Value</attributes>
              <propertyType></propertyType>
          </com.axibase.collector.model.job.jmx.TrackingMBean>
        </trackingMBeans>
        <entity></entity>
        <metricPrefix></metricPrefix>
        <propertyTypePrefix>jmx.kafka.</propertyTypePrefix>
        <serviceName></serviceName>
        <excludedMetrics>
          <string>75thPercentile</string>
          <string>95thPercentile</string>
          <string>98thPercentile</string>
          <string>999thPercentile</string>
          <string>EventType</string>
          <string>FifteenMinuteRate</string>
          <string>LatencyUnit</string>
          <string>RateUnit</string>
          <string>StdDev</string>
        </excludedMetrics>
        <excludedProperties/>
        <seriesTags/>
        <putType>PROPERTY</putType>
      </com.axibase.collector.model.job.jmx.JmxConfiguration>
    </configurations>
  </com.axibase.collector.model.job.jmx.JmxJobConfig>
</list>